hooks/__init__.py
hooks/banner.py
hooks/check_any_types.js
hooks/check_commented_code.py
hooks/check_console_error.py
hooks/check_debug_statements.py
hooks/check_deep_nesting.py
hooks/check_docker_platform.py
hooks/check_dry_violations.js
hooks/check_dry_violations.py
hooks/check_empty_catch.py
hooks/check_function_length.py
hooks/check_hardcoded_urls.py
hooks/check_magic_numbers.py
hooks/check_secrets.py
hooks/check_snake_case_ts.js
hooks/check_todo_fixme.py
hooks/check_unsafe_html.js
vibe_and_thrive-0.3.0.dist-info/METADATA
vibe_and_thrive-0.3.0.dist-info/WHEEL
vibe_and_thrive-0.3.0.dist-info/entry_points.txt
vibe_and_thrive-0.3.0.dist-info/licenses/LICENSE
vibe_and_thrive-0.3.0.dist-info/RECORD
