Metadata-Version: 2.4
Name: vibe-and-thrive
Version: 0.3.0
Summary: Tools and guardrails that catch common AI coding mistakes before they hit your codebase
Project-URL: Homepage, https://github.com/allthriveai/vibe-and-thrive
Project-URL: Documentation, https://github.com/allthriveai/vibe-and-thrive#readme
Project-URL: Repository, https://github.com/allthriveai/vibe-and-thrive.git
Project-URL: Issues, https://github.com/allthriveai/vibe-and-thrive/issues
Author-email: AllThrive AI <hello@allthrive.ai>
License-Expression: MIT
License-File: LICENSE
Keywords: ai,claude,code-quality,coding,copilot,cursor,linting,pre-commit,vibe-coding
Classifier: Development Status :: 4 - Beta
Classifier: Environment :: Console
Classifier: Intended Audience :: Developers
Classifier: License :: OSI Approved :: MIT License
Classifier: Operating System :: OS Independent
Classifier: Programming Language :: Python :: 3
Classifier: Programming Language :: Python :: 3.10
Classifier: Programming Language :: Python :: 3.11
Classifier: Programming Language :: Python :: 3.12
Classifier: Topic :: Software Development :: Quality Assurance
Classifier: Topic :: Software Development :: Testing
Requires-Python: >=3.10
Provides-Extra: dev
Requires-Dist: pytest-cov>=4.0.0; extra == 'dev'
Requires-Dist: pytest>=7.0.0; extra == 'dev'
